{
  "db_name": "PostgreSQL",
  "query": "SELECT * FROM payroll_groups WHERE company_id = $1 AND is_active = TRUE ORDER BY name",
  "describe": {
    "columns": [
      {
        "ordinal": 0,
        "name": "id",
        "type_info": "Uuid"
      },
      {
        "ordinal": 1,
        "name": "company_id",
        "type_info": "Uuid"
      },
      {
        "ordinal": 2,
        "name": "name",
        "type_info": "Varchar"
      },
      {
        "ordinal": 3,
        "name": "description",
        "type_info": "Varchar"
      },
      {
        "ordinal": 4,
        "name": "cutoff_day",
        "type_info": "Int4"
      },
      {
        "ordinal": 5,
        "name": "payment_day",
        "type_info": "Int4"
      },
      {
        "ordinal": 6,
        "name": "is_active",
        "type_info": "Bool"
      },
      {
        "ordinal": 7,
        "name": "created_at",
        "type_info": "Timestamptz"
      },
      {
        "ordinal": 8,
        "name": "updated_at",
        "type_info": "Timestamptz"
      },
      {
        "ordinal": 9,
        "name": "created_by",
        "type_info": "Uuid"
      },
      {
        "ordinal": 10,
        "name": "updated_by",
        "type_info": "Uuid"
      }
    ],
    "parameters": {
      "Left": [
        "Uuid"
      ]
    },
    "nullable": [
      false,
      false,
      false,
      true,
      false,
      false,
      true,
      false,
      false,
      true,
      true
    ]
  },
  "hash": "8563004e84480bdbea6d8ca455311eb46af128077194768607da4e0cc7e986d8"
}
