{
  "db_name": "PostgreSQL",
  "query": "UPDATE payroll_entries\n        SET employee_id = $3,\n            period_year = $4,\n            period_month = $5,\n            category = $6,\n            item_type = $7,\n            description = $8,\n            amount = $9,\n            quantity = $10,\n            rate = $11,\n            is_taxable = COALESCE($12, is_taxable),\n            updated_by = $13,\n            updated_at = NOW()\n        WHERE id = $1 AND company_id = $2 AND is_processed = FALSE\n        RETURNING *",
  "describe": {
    "columns": [
      {
        "ordinal": 0,
        "name": "id",
        "type_info": "Uuid"
      },
      {
        "ordinal": 1,
        "name": "employee_id",
        "type_info": "Uuid"
      },
      {
        "ordinal": 2,
        "name": "company_id",
        "type_info": "Uuid"
      },
      {
        "ordinal": 3,
        "name": "period_year",
        "type_info": "Int4"
      },
      {
        "ordinal": 4,
        "name": "period_month",
        "type_info": "Int4"
      },
      {
        "ordinal": 5,
        "name": "category",
        "type_info": "Varchar"
      },
      {
        "ordinal": 6,
        "name": "item_type",
        "type_info": "Varchar"
      },
      {
        "ordinal": 7,
        "name": "description",
        "type_info": "Varchar"
      },
      {
        "ordinal": 8,
        "name": "amount",
        "type_info": "Int8"
      },
      {
        "ordinal": 9,
        "name": "quantity",
        "type_info": "Numeric"
      },
      {
        "ordinal": 10,
        "name": "rate",
        "type_info": "Int8"
      },
      {
        "ordinal": 11,
        "name": "is_taxable",
        "type_info": "Bool"
      },
      {
        "ordinal": 12,
        "name": "is_processed",
        "type_info": "Bool"
      },
      {
        "ordinal": 13,
        "name": "payroll_run_id",
        "type_info": "Uuid"
      },
      {
        "ordinal": 14,
        "name": "created_at",
        "type_info": "Timestamptz"
      },
      {
        "ordinal": 15,
        "name": "updated_at",
        "type_info": "Timestamptz"
      },
      {
        "ordinal": 16,
        "name": "created_by",
        "type_info": "Uuid"
      },
      {
        "ordinal": 17,
        "name": "updated_by",
        "type_info": "Uuid"
      }
    ],
    "parameters": {
      "Left": [
        "Uuid",
        "Uuid",
        "Uuid",
        "Int4",
        "Int4",
        "Varchar",
        "Varchar",
        "Varchar",
        "Int8",
        "Numeric",
        "Int8",
        "Bool",
        "Uuid"
      ]
    },
    "nullable": [
      false,
      false,
      false,
      false,
      false,
      false,
      false,
      false,
      false,
      true,
      true,
      true,
      true,
      true,
      false,
      false,
      true,
      true
    ]
  },
  "hash": "8a1c0c53354d59f68981960ffe001f5fd7c97d61738fc990ec5fb86de1b4b69c"
}
