{
  "db_name": "PostgreSQL",
  "query": "INSERT INTO payroll_entries\n            (employee_id, company_id, period_year, period_month, category, item_type,\n             description, amount, quantity, rate, is_taxable, created_by)\n        VALUES ($1, $2, $3, $4, $5, $6, $7, $8, $9, $10, COALESCE($11, TRUE), $12)\n        RETURNING *",
  "describe": {
    "columns": [
      {
        "ordinal": 0,
        "name": "id",
        "type_info": "Uuid"
      },
      {
        "ordinal": 1,
        "name": "employee_id",
        "type_info": "Uuid"
      },
      {
        "ordinal": 2,
        "name": "company_id",
        "type_info": "Uuid"
      },
      {
        "ordinal": 3,
        "name": "period_year",
        "type_info": "Int4"
      },
      {
        "ordinal": 4,
        "name": "period_month",
        "type_info": "Int4"
      },
      {
        "ordinal": 5,
        "name": "category",
        "type_info": "Varchar"
      },
      {
        "ordinal": 6,
        "name": "item_type",
        "type_info": "Varchar"
      },
      {
        "ordinal": 7,
        "name": "description",
        "type_info": "Varchar"
      },
      {
        "ordinal": 8,
        "name": "amount",
        "type_info": "Int8"
      },
      {
        "ordinal": 9,
        "name": "quantity",
        "type_info": "Numeric"
      },
      {
        "ordinal": 10,
        "name": "rate",
        "type_info": "Int8"
      },
      {
        "ordinal": 11,
        "name": "is_taxable",
        "type_info": "Bool"
      },
      {
        "ordinal": 12,
        "name": "is_processed",
        "type_info": "Bool"
      },
      {
        "ordinal": 13,
        "name": "payroll_run_id",
        "type_info": "Uuid"
      },
      {
        "ordinal": 14,
        "name": "created_at",
        "type_info": "Timestamptz"
      },
      {
        "ordinal": 15,
        "name": "updated_at",
        "type_info": "Timestamptz"
      },
      {
        "ordinal": 16,
        "name": "created_by",
        "type_info": "Uuid"
      },
      {
        "ordinal": 17,
        "name": "updated_by",
        "type_info": "Uuid"
      }
    ],
    "parameters": {
      "Left": [
        "Uuid",
        "Uuid",
        "Int4",
        "Int4",
        "Varchar",
        "Varchar",
        "Varchar",
        "Int8",
        "Numeric",
        "Int8",
        "Bool",
        "Uuid"
      ]
    },
    "nullable": [
      false,
      false,
      false,
      false,
      false,
      false,
      false,
      false,
      false,
      true,
      true,
      true,
      true,
      true,
      false,
      false,
      true,
      true
    ]
  },
  "hash": "8f44aeb288a705a01779a76b216509f71723a66efece0e427d43701a2e127b01"
}
